gradio_tabulalite/__init__.py
gradio_tabulalite/tabulalite.py
gradio_tabulalite/tabulalite.pyi
gradio_tabulalite/templates/component/index.js
gradio_tabulalite/templates/component/style.css
gradio_tabulalite/templates/example/index.js
gradio_tabulalite/templates/example/style.css
gradio_tabulalite-0.6.22.dist-info/METADATA
gradio_tabulalite-0.6.22.dist-info/WHEEL
gradio_tabulalite-0.6.22.dist-info/RECORD
