Metadata-Version: 2.4
Name: gradio_tabulalite
Version: 0.6.22
Summary: a lightweight, feature-rich Gradio custom component for displaying interactive data tables with built-in sorting, pagination, search, row selection, and CSV export — all wrapped in a beautiful light-orange theme
Author: Yufeng Chen
License-Expression: MIT
Keywords: custom-component,data-table,datatable,export-csv,filterable-table,frontend-svelte,gradio,gradio-component,gradio-custom-component,gradio-table,gradio-template-Fallback,interactive-table,paginated-table,python-table,row-selection,sortable-table,table-search,tabulalite
Classifier: Development Status :: 3 - Alpha
Classifier: Operating System :: OS Independent
Classifier: Programming Language :: Python :: 3
Classifier: Programming Language :: Python :: 3 :: Only
Classifier: Programming Language :: Python :: 3.8
Classifier: Programming Language :: Python :: 3.9
Classifier: Programming Language :: Python :: 3.10
Classifier: Programming Language :: Python :: 3.11
Classifier: Topic :: Scientific/Engineering
Classifier: Topic :: Scientific/Engineering :: Artificial Intelligence
Classifier: Topic :: Scientific/Engineering :: Visualization
Requires-Python: >=3.10
Requires-Dist: gradio<6.0,>=4.0
Provides-Extra: dev
Requires-Dist: build; extra == 'dev'
Requires-Dist: twine; extra == 'dev'
